httpxx/__init__.py
httpxx/core.py
httpxx-0.1.2.dist-info/METADATA
httpxx-0.1.2.dist-info/WHEEL
httpxx-0.1.2.dist-info/licenses/LICENSE
httpxx-0.1.2.dist-info/RECORD
