Metadata-Version: 2.4
Name: httpxx
Version: 0.1.2
Summary: httpx的封装
License: MIT
License-File: LICENSE
Keywords: cache,http,httpx
Requires-Python: >=3.8
Requires-Dist: httpx>=0.28.1
